{"class":"DepictionTabView","tabs":[{"class":"DepictionStackView","tabname":"Details","views":[{"class":"DepictionSpacerView","spacing":12},{"text":"Click here to buy me a coffee :)","class":"DepictionButtonView","action":"https:\/\/paypal.me\/borkarprajakta\/5","yPadding":10},{"markdown":"No Ads in the NDTV News App!","class":"DepictionMarkdownView"},{"class":"DepictionSeparatorView"},{"class":"DepictionTableButtonView","action":"https:\/\/github.com\/p2kdev\/NDTVNoAds","title":"View source code"},{"class":"DepictionSeparatorView"},{"class":"DepictionHeaderView","title":"Extra information"},{"title":"Version","class":"DepictionTableTextView","text":"1.0.1"},{"class":"DepictionTableButtonView","action":"https:\/\/twitter.com\/p2kdev","title":"Twitter"},{"class":"DepictionTableButtonView","action":"mailto:p2kdev@gmail.com?subject=NDTVNoAds","title":"Email"},{"action":"https:\/\/p2kdev.github.io\/repo\/depictions\/index.html?packageId=com.p2kdev.ndtvnoads","class":"DepictionTableButtonView","title":"View web depiction"}]},{"views":[{"views":[{"title":"1.0.1","useBoldText":true,"alignment":0,"class":"DepictionSubheaderView"},{"title":"2023-05-19","class":"DepictionSubheaderView","alignment":2}],"class":"DepictionLayerView"},{"useSpacing":true,"class":"DepictionMarkdownView","markdown":"- Initial release on the repo"},{"class":"DepictionSpacerView","spacing":12}],"class":"DepictionStackView","tabname":"Changes"}],"tintColor":"#47afd1","minVersion":"0.4","headerImage":"https:\/\/p2kdev.github.io\/repo\/api\/packageinfo\/com.p2kdev.ndtvnoads\/banner.png"}
