{"tabs":[{"tabname":"Details","class":"DepictionStackView","views":[{"spacing":12,"class":"DepictionSpacerView"},{"action":"https:\/\/paypal.me\/borkarprajakta\/5","text":"Click here to buy me a coffee :)","class":"DepictionButtonView","yPadding":10},{"markdown":"Single List of Notifications!","class":"DepictionMarkdownView"},{"class":"DepictionSeparatorView"},{"class":"DepictionTableButtonView","title":"View source code","action":"https:\/\/github.com\/p2kdev\/KeepItSimple"},{"class":"DepictionSeparatorView"},{"title":"Extra information","class":"DepictionHeaderView"},{"text":"1.2.3","class":"DepictionTableTextView","title":"Version"},{"action":"https:\/\/twitter.com\/p2kdev","title":"Twitter","class":"DepictionTableButtonView"},{"class":"DepictionTableButtonView","action":"mailto:p2kdev@gmail.com?subject=KeepItSimple","title":"Email"},{"action":"https:\/\/p2kdev.github.io\/repo\/depictions\/index.html?packageId=com.p2kdev.keepitsimple","title":"View web depiction","class":"DepictionTableButtonView"}]},{"class":"DepictionStackView","views":[{"class":"DepictionLayerView","views":[{"title":"1.2.3","alignment":0,"useBoldText":true,"class":"DepictionSubheaderView"},{"title":"2024-02-06","class":"DepictionSubheaderView","alignment":2}]},{"class":"DepictionMarkdownView","useSpacing":true,"markdown":"- iOS16 Support"},{"class":"DepictionSpacerView","spacing":12},{"class":"DepictionLayerView","views":[{"alignment":0,"class":"DepictionSubheaderView","useBoldText":true,"title":"1.2.2"},{"title":"2023-05-19","alignment":2,"class":"DepictionSubheaderView"}]},{"useSpacing":true,"class":"DepictionMarkdownView","markdown":"- Initial release on the repo"},{"class":"DepictionSpacerView","spacing":12}],"tabname":"Changes"}],"tintColor":"#47afd1","headerImage":"https:\/\/p2kdev.github.io\/repo\/api\/packageinfo\/com.p2kdev.keepitsimple\/banner.png","class":"DepictionTabView","minVersion":"0.4"}
