{"class":"DepictionTabView","tintColor":"#47afd1","tabs":[{"class":"DepictionStackView","views":[{"spacing":12,"class":"DepictionSpacerView"},{"class":"DepictionButtonView","action":"https:\/\/paypal.me\/borkarprajakta\/5","yPadding":10,"text":"Click here to buy me a coffee :)"},{"class":"DepictionMarkdownView","markdown":"Always show the full update changelog in AppStore!"},{"class":"DepictionSeparatorView"},{"class":"DepictionTableButtonView","title":"View source code","action":"https:\/\/github.com\/p2kdev\/AppStoreNoMoreBtn"},{"class":"DepictionSeparatorView"},{"class":"DepictionHeaderView","title":"Extra information"},{"class":"DepictionTableTextView","text":"1.0-29+debug","title":"Version"},{"action":"https:\/\/twitter.com\/p2kdev","class":"DepictionTableButtonView","title":"Twitter"},{"action":"mailto:p2kdev@gmail.com?subject=AppStoreNoMoreBtn","title":"Email","class":"DepictionTableButtonView"},{"action":"https:\/\/p2kdev.github.io\/repo\/depictions\/index.html?packageId=com.imkpatil.appstorenomorebtn","class":"DepictionTableButtonView","title":"View web depiction"}],"tabname":"Details"},{"tabname":"Changes","views":[{"views":[{"class":"DepictionSubheaderView","useBoldText":true,"title":"1.0-29+debug","alignment":0},{"class":"DepictionSubheaderView","alignment":2,"title":"2023-05-19"}],"class":"DepictionLayerView"},{"class":"DepictionMarkdownView","markdown":"- Initial release on the repo","useSpacing":true},{"class":"DepictionSpacerView","spacing":12}],"class":"DepictionStackView"}],"minVersion":"0.4","headerImage":"https:\/\/p2kdev.github.io\/repo\/api\/packageinfo\/com.imkpatil.appstorenomorebtn\/banner.png"}
