{"headerImage":"https:\/\/p2kdev.github.io\/repo\/api\/packageinfo\/com.p2kdev.whatsappmultideviceenable\/banner.png","minVersion":"0.4","class":"DepictionTabView","tintColor":"#47afd1","tabs":[{"views":[{"spacing":12,"class":"DepictionSpacerView"},{"text":"Click here to buy me a coffee :)","action":"https:\/\/paypal.me\/borkarprajakta\/5","yPadding":10,"class":"DepictionButtonView"},{"markdown":"Force Enables the Multi-Device linking on WhatsApp!","class":"DepictionMarkdownView"},{"class":"DepictionSeparatorView"},{"title":"Extra information","class":"DepictionHeaderView"},{"text":"1.0","title":"Version","class":"DepictionTableTextView"},{"action":"https:\/\/twitter.com\/p2kdev","title":"Twitter","class":"DepictionTableButtonView"},{"action":"mailto:p2kdev@gmail.com?subject=WhatsAppMultiDeviceEnable","title":"Email","class":"DepictionTableButtonView"},{"action":"https:\/\/p2kdev.github.io\/repo\/depictions\/index.html?packageId=com.p2kdev.whatsappmultideviceenable","title":"View web depiction","class":"DepictionTableButtonView"}],"tabname":"Details","class":"DepictionStackView"},{"views":[{"class":"DepictionLayerView","views":[{"title":"1.0","useBoldText":true,"class":"DepictionSubheaderView","alignment":0},{"title":"2023-05-19","class":"DepictionSubheaderView","alignment":2}]},{"class":"DepictionMarkdownView","useSpacing":true,"markdown":"- Initial release on the repo"},{"spacing":12,"class":"DepictionSpacerView"}],"tabname":"Changes","class":"DepictionStackView"}]}
