{"tintColor":"#47afd1","tabs":[{"class":"DepictionStackView","views":[{"spacing":12,"class":"DepictionSpacerView"},{"action":"https:\/\/paypal.me\/borkarprajakta\/5","text":"Click here to buy me a coffee :)","yPadding":10,"class":"DepictionButtonView"},{"markdown":"No Ads in the Twitter App!","class":"DepictionMarkdownView"},{"class":"DepictionSeparatorView"},{"class":"DepictionHeaderView","title":"Extra information"},{"text":"1.2.6","class":"DepictionTableTextView","title":"Version"},{"action":"https:\/\/twitter.com\/p2kdev","class":"DepictionTableButtonView","title":"Twitter"},{"action":"mailto:p2kdev@gmail.com?subject=TwitterNoAds","class":"DepictionTableButtonView","title":"Email"},{"action":"https:\/\/p2kdev.github.io\/repo\/depictions\/index.html?packageId=com.p2kdev.twitternoads","class":"DepictionTableButtonView","title":"View web depiction"}],"tabname":"Details"},{"class":"DepictionStackView","views":[{"views":[{"class":"DepictionSubheaderView","alignment":0,"useBoldText":true,"title":"1.2.6"},{"class":"DepictionSubheaderView","alignment":2,"title":"2025-05-14"}],"class":"DepictionLayerView"},{"markdown":" - Disable twitter expermental feature of pausing autoplay videos.\n - Added support for picture-in-picture mode for videos.","useSpacing":true,"class":"DepictionMarkdownView"},{"class":"DepictionSpacerView","spacing":12},{"views":[{"class":"DepictionSubheaderView","alignment":0,"useBoldText":true,"title":"1.2.5"},{"class":"DepictionSubheaderView","alignment":2,"title":"2025-01-12"}],"class":"DepictionLayerView"},{"markdown":"Hide Trending posts","useSpacing":true,"class":"DepictionMarkdownView"},{"class":"DepictionSpacerView","spacing":12},{"views":[{"class":"DepictionSubheaderView","title":"1.2.4","useBoldText":true,"alignment":0},{"class":"DepictionSubheaderView","title":"2024-08-19","alignment":2}],"class":"DepictionLayerView"},{"markdown":"Hide Google Ads","useSpacing":true,"class":"DepictionMarkdownView"},{"class":"DepictionSpacerView","spacing":12},{"views":[{"title":"1.2.3","class":"DepictionSubheaderView","alignment":0,"useBoldText":true},{"title":"2024-07-16","class":"DepictionSubheaderView","alignment":2}],"class":"DepictionLayerView"},{"markdown":"Fix some posts not hiding","useSpacing":true,"class":"DepictionMarkdownView"},{"class":"DepictionSpacerView","spacing":12},{"class":"DepictionLayerView","views":[{"alignment":0,"useBoldText":true,"title":"1.2.2","class":"DepictionSubheaderView"},{"alignment":2,"title":"2024-04-25","class":"DepictionSubheaderView"}]},{"class":"DepictionMarkdownView","useSpacing":true,"markdown":"Fix new tweet indicator"},{"class":"DepictionSpacerView","spacing":12},{"class":"DepictionLayerView","views":[{"class":"DepictionSubheaderView","useBoldText":true,"alignment":0,"title":"1.2.1"},{"class":"DepictionSubheaderView","alignment":2,"title":"2024-04-16"}]},{"class":"DepictionMarkdownView","useSpacing":true,"markdown":"Hide all recommended posts"},{"spacing":12,"class":"DepictionSpacerView"},{"views":[{"class":"DepictionSubheaderView","useBoldText":true,"alignment":0,"title":"1.2"},{"class":"DepictionSubheaderView","alignment":2,"title":"2024-04-06"}],"class":"DepictionLayerView"},{"markdown":"Hide Pinned & suggested posts","useSpacing":true,"class":"DepictionMarkdownView"},{"spacing":12,"class":"DepictionSpacerView"},{"views":[{"class":"DepictionSubheaderView","title":"1.1.1","useBoldText":true,"alignment":0},{"class":"DepictionSubheaderView","title":"2023-05-24","alignment":2}],"class":"DepictionLayerView"},{"markdown":"Fixed related tweets. Thanks [FoxfortMobile](https:\/\/twitter.com\/FoxfortMobile)","useSpacing":true,"class":"DepictionMarkdownView"},{"spacing":12,"class":"DepictionSpacerView"},{"views":[{"alignment":0,"title":"1.1","class":"DepictionSubheaderView","useBoldText":true},{"alignment":2,"title":"2023-05-19","class":"DepictionSubheaderView"}],"class":"DepictionLayerView"},{"markdown":"Initial release on the repo","useSpacing":true,"class":"DepictionMarkdownView"},{"spacing":12,"class":"DepictionSpacerView"}],"tabname":"Changes"}],"class":"DepictionTabView","minVersion":"0.4","headerImage":"https:\/\/p2kdev.github.io\/repo\/api\/packageinfo\/com.p2kdev.twitternoads\/banner.png"}
